closurizer/cli.py
closurizer/closurizer.py
closurizer-0.8.1.dist-info/METADATA
closurizer-0.8.1.dist-info/WHEEL
closurizer-0.8.1.dist-info/entry_points.txt
closurizer-0.8.1.dist-info/RECORD
