Metadata-Version: 2.3
Name: closurizer
Version: 0.8.1
Summary: Add closure expansion fields to kgx files following the Golr pattern
Author: Kevin Schaper
Author-email: kevin@tislab.org
Requires-Python: >=3.8,<4.0
Classifier: Programming Language :: Python :: 3
Classifier: Programming Language :: Python :: 3.8
Classifier: Programming Language :: Python :: 3.9
Classifier: Programming Language :: Python :: 3.10
Classifier: Programming Language :: Python :: 3.11
Classifier: Programming Language :: Python :: 3.12
Classifier: Programming Language :: Python :: 3.13
Requires-Dist: SQLAlchemy (>=1.4.37,<2.0.0)
Requires-Dist: click (>=8,<9)
Requires-Dist: duckdb
